arctic_spa/__init__.py
arctic_spa/arctic_spa.py
arctic_spa/discovery.py
arctic_spa/proto/arctic_spa_pb2.py
arctic_spa-0.0.1.dist-info/METADATA
arctic_spa-0.0.1.dist-info/WHEEL
arctic_spa-0.0.1.dist-info/licenses/LICENSE
arctic_spa-0.0.1.dist-info/RECORD
