Metadata-Version: 2.1
Name: arctic_spa
Version: 0.0.1
Summary: An interface to Arctic Spa hot tubs
Project-URL: Homepage, https://github.com/xxv/arctic-spa
Project-URL: Bug Tracker, https://github.com/xxv/arctic-spa/issues
Author-email: Steve Pomeroy <steve@staticfree.info>
License-File: LICENSE
Classifier: License :: OSI Approved :: Apache Software License
Classifier: Operating System :: OS Independent
Classifier: Programming Language :: Python :: 3
Requires-Python: >=3.7
Requires-Dist: protobuf==3.20.0
